
{
  "appId": "com.sarvari.sellerpro.pos",
  "appName": "Sarvari Seller Pro",
  "webDir": ".",
  "bundledWebRuntime": false,
  "server": {
    "androidScheme": "https",
    "allowNavigation": ["*"]
  },
  "android": {
    "allowMixedContent": true,
    "captureInput": true,
    "webContentsDebuggingEnabled": true
  },
  "plugins": {
    "SplashScreen": {
      "launchShowDuration": 3000,
      "launchAutoHide": true,
      "backgroundColor": "#4f46e5",
      "androidSplashResourceName": "splash",
      "androidScaleType": "CENTER_CROP",
      "showSpinner": true,
      "androidSpinnerStyle": "large",
      "spinnerColor": "#ffffff"
    }
  }
}
